object_clerk/__init__.py
object_clerk/clerk.py
object_clerk/config.py
object_clerk/exceptions.py
object_clerk/utils.py
object_clerk/tests/__init__.py
object_clerk/tests/example_object
object_clerk/tests/test_object_clerk.py
object_clerk-1.0.1.dist-info/licenses/LICENSE
object_clerk-1.0.1.dist-info/METADATA
object_clerk-1.0.1.dist-info/WHEEL
object_clerk-1.0.1.dist-info/top_level.txt
object_clerk-1.0.1.dist-info/RECORD
