Metadata-Version: 2.4
Name: object-clerk
Version: 1.0.1
Summary: A wrapper for select object operations using boto3 for Ceph which confirms integrity of reads and heals intermittent connectivity.
Author-email: NSO / AURA <dkistdc@nso.edu>
License: MIT
Project-URL: repository, https://bitbucket.org/dkistdc/object_clerk
Classifier: Programming Language :: Python
Classifier: Programming Language :: Python :: 3 :: Only
Classifier: Programming Language :: Python :: 3.11
Classifier: Programming Language :: Python :: 3.12
Classifier: Programming Language :: Python :: 3.13
Requires-Python: >=3.11
License-File: LICENSE
Requires-Dist: boto3~=1.11
Requires-Dist: tenacity<10.0,>=8.2
Requires-Dist: pydantic~=2.0
Provides-Extra: test
Requires-Dist: pytest; extra == "test"
Requires-Dist: pytest-cov; extra == "test"
Dynamic: license-file
